statx/__init__.py
pystatx-0.1.dist-info/LICENSE
pystatx-0.1.dist-info/METADATA
pystatx-0.1.dist-info/WHEEL
pystatx-0.1.dist-info/top_level.txt
pystatx-0.1.dist-info/RECORD
